<?xml version="1.0" encoding="UTF-8"?>
<SlimOTA xmlns:xsi="http://www.w3.org/2001/XMLSchema-instance" xsi:noNamespaceSchemaLocation="ota.xsd">
    <Stable>
        <wt88047>
            <Filename>Tesla-wt88047-6.0.1.RC.1.v2.2-Official-20160724.zip</Filename>
            <RomUrl
                id="rom"
                title="Rom"
                description="Download TeslaM build">https://www.androidfilehost.com/?fid=24591000424949507</RomUrl>
            <ChangelogUrl
                id="changelog"
                title="Changelog"
                description="View TeslaM changelogs">https://github.com/Tesla-M/OTA_config/blob/master/Changelogs/Xiaomi/wt88047/Changelog.txt</ChangelogUrl>
            <GappsUrl
                id="gapps"
                title="Gapps"
                description="Download latest Banks gapps">https://www.androidfilehost.com/?w=files&amp;flid=41020</GappsUrl>
            <XDAUrl
                id="xda"
                title="XDA"
                description="Visit TeslaM Redmi-2 XDA thread">http://forum.xda-developers.com/redmi-2/development/rom-tesla-rom-t3330248</XDAUrl>
        </wt88047>
        <huashan>
            <Filename>Tesla-huashan-6.0.1.RC.1.v2.2-Official-20160727.zip</Filename>
            <RomUrl
                id="rom"
                title="Rom"
                description="Download Tesla build">https://www.androidfilehost.com/?fid=24651429356503376</RomUrl>
            <ChangelogUrl
                id="changelog"
                title="Changelog"
                description="View Tesla changelogs">https://github.com/Tesla-M/OTA_config/blob/master/Changelogs/Sony/huashan/Changelog.txt</ChangelogUrl>
            <GappsUrl
                id="gapps"
                title="Gapps"
                description="Download latest Banks gapps">https://www.androidfilehost.com/?w=files&amp;flid=41020</GappsUrl>
            <XDAUrl
                id="xda"
                title="XDA"
                description="Visit Tesla Xperia SP XDA thread">http://forum.xda-developers.com/xperia-sp/development/rom-6-0-1r46-ubertc-4-9-gzr-tesla-v2-1-t3397692</XDAUrl>
        </huashan>
        <C6603>
            <Filename>Tesla-yuga-6.0.1.OMS.v2.3-Official-20160731-2005</Filename>
            <RomUrl
                id="rom"
                title="Rom"
                description="Download latest Tesla build">https://www.androidfilehost.com/?fid=24591000424951273</RomUrl>
            <ChangelogUrl
                id="changelog"
                title="Changelog"
                description="View Tesla changelogs">https://github.com/Tesla-M/OTA_config/blob/master/Changelogs/Sony/yuga/Changelog.txt</ChangelogUrl>
            <GappsUrl
                id="gapps"
                title="Gapps"
                description="Download latest Banks gapps">https://www.androidfilehost.com/?w=files&amp;flid=41020</GappsUrl>
            <XDAUrl
                id="xda"
                title="XDA"
                description="Visit Tesla yuga thread">http://forum.xda-developers.com/xperia-z/development/rom-tesla-rom-official-ground-zero-roms-t3348105</XDAUrl>
        </C6603>
        <lux>
            <Filename>Tesla-lux-6.0.1.OMS.v2.3-Official</Filename>
            <RomUrl
                id="rom"
                title="Rom"
                description="Download latest Tesla build">https://www.androidfilehost.com/?fid=24591000424949907</RomUrl>
            <ChangelogUrl
                id="changelog"
                title="Changelog"
                description="View Tesla changelogs">https://github.com/Tesla-M/OTA_config/blob/master/Changelogs/Motorola/lux/Changelog.txt</ChangelogUrl>
            <GappsUrl
                id="gapps"
                title="Gapps"
                description="Download latest Banks gapps">https://www.androidfilehost.com/?w=files&amp;flid=41020</GappsUrl>
            <XDAUrl
                id="xda"
                title="XDA"
                description="Visit Tesla lux thread">http://forum.xda-developers.com/moto-x-play/development/rom-tesla-rom-6-0-1r13-t3310336</XDAUrl>
        </lux>
        <shieldtablet>
            <Filename>Tesla-shieldtablet-6.0.1.OMS.v2.3-Official</Filename>
            <RomUrl
                id="rom"
                title="Rom"
                description="Download latest Tesla build">https://www.androidfilehost.com/?fid=24591000424949912</RomUrl>
            <ChangelogUrl
                id="changelog"
                title="Changelog"
                description="View Tesla changelogs">https://github.com/Tesla-M/OTA_config/blob/master/Changelogs/Nvidia/shieldtablet/Changelog.txt</ChangelogUrl>
            <GappsUrl
                id="gapps"
                title="Gapps"
                description="Download latest Banks gapps">https://www.androidfilehost.com/?w=files&amp;flid=41020</GappsUrl>
            <XDAUrl
                id="xda"
                title="XDA"
                description="Visit Tesla shieldtablet thread">http://forum.xda-developers.com/shield-tablet/development/rom-tesla-6-0-1r46-t3410432</XDAUrl>
        </shieldtablet>
    </Stable>
</SlimOTA>
